tpds_extension/dspic33_support/extension.yaml
tpds_extension/dspic33_support/setup.py
tpds_extension/dspic33_support/version.py
tpds_extension/dspic33_support/backend/__init__.py
tpds_extension/dspic33_support/backend/boards/DM240001-2.yaml
tpds_extension/dspic33_support/backend/boards/DM240001-2/DM240001-2.png
tpds_extension_dspic33_support-1.0.1.dist-info/METADATA
tpds_extension_dspic33_support-1.0.1.dist-info/WHEEL
tpds_extension_dspic33_support-1.0.1.dist-info/top_level.txt
tpds_extension_dspic33_support-1.0.1.dist-info/RECORD
