Metadata-Version: 2.1
Name: tpds-extension-dspic33-support
Version: 1.0.1
Summary: Microchip(SPG) Trust Platform - dsPIC33 extension
Home-page: https://www.microchip.com/TrustPlatform
Author: Microchip Technology
Author-email: SPG.Tools@microchip.com
Classifier: License :: Other/Proprietary License
Classifier: Development Status :: 4 - Beta
Classifier: Programming Language :: Python :: 3
Classifier: Operating System :: OS Independent
Requires-Python: >=3.8
Requires-Dist: tpds-core >=2.3.18
Requires-Dist: tpds-helper >=2.3.14
Requires-Dist: pykitinfo >=1.1.2.19
